server.py
memory_journal_mcp_server-0.1.0.dist-info/METADATA
memory_journal_mcp_server-0.1.0.dist-info/WHEEL
memory_journal_mcp_server-0.1.0.dist-info/top_level.txt
memory_journal_mcp_server-0.1.0.dist-info/RECORD
