Metadata-Version: 2.2
Name: memory-journal-mcp-server
Version: 0.1.0
Summary: MCP server for memory journal from local photos (iCloud Photos)
Author-email: Siddhant Khare <siddhantkhare2694@gmail.com>
Requires-Python: >=3.11
Requires-Dist: dateparser>=1.2.0
Requires-Dist: httpx>=0.28.1
Requires-Dist: mcp>=1.2.0
Requires-Dist: osxphotos>=0.69.2
Requires-Dist: spacy>=3.8.4
Requires-Dist: thefuzz>=0.22.1
